ChasmSystem/Die_Class.py
ChasmSystem/Entity_Class.py
ChasmSystem/Game_Master_Class.py
ChasmSystem/Global_Config.py
ChasmSystem/Weapon_Class.py
ChasmSystem/__init__.py
ChasmSystem-0.0.4.dist-info/METADATA
ChasmSystem-0.0.4.dist-info/WHEEL
ChasmSystem-0.0.4.dist-info/top_level.txt
ChasmSystem-0.0.4.dist-info/RECORD
