Metadata-Version: 2.1
Name: ChasmSystem
Version: 0.0.4
